daniel_eos/__init__.py
daniel_eos/config.py
daniel_eos/http_requests.py
daniel_eos/response_json.py
daniel_eos/upload.py
daniel_eos/daniel_eos.egg-info/PKG-INFO
daniel_eos/daniel_eos.egg-info/SOURCES.txt
daniel_eos/daniel_eos.egg-info/dependency_links.txt
daniel_eos/daniel_eos.egg-info/requires.txt
daniel_eos/daniel_eos.egg-info/top_level.txt
daniel_eos-1.0.dist-info/METADATA
daniel_eos-1.0.dist-info/WHEEL
daniel_eos-1.0.dist-info/licenses/LICENSE
daniel_eos-1.0.dist-info/RECORD
