Metadata-Version: 2.3
Name: daniel_eos
Version: 1.0
Summary: daniel_eos is a package for eos to yidongyun 
Project-URL: Homepage, https://github.com/NickYi1990/juans
Author-email: Daniel Chen <cdmstrong123@gmail.com>
License:                     GNU GENERAL PUBLIC LICENSE
Classifier: License :: OSI Approved :: MIT License
Classifier: Operating System :: OS Independent
Classifier: Programming Language :: Python :: 3
Requires-Python: >=3.9
Requires-Dist: aiohttp
Requires-Dist: boto3==1.35.92
Requires-Dist: pydantic
Requires-Dist: requests
